teiphy/__init__.py
teiphy/collation.py
teiphy/common.py
teiphy/format.py
teiphy/main.py
teiphy/reading.py
teiphy/templates/beast_template.xml
teiphy/variation_unit.py
teiphy/witness.py
teiphy-0.1.23.dist-info/LICENSE
teiphy-0.1.23.dist-info/METADATA
teiphy-0.1.23.dist-info/WHEEL
teiphy-0.1.23.dist-info/entry_points.txt
teiphy-0.1.23.dist-info/RECORD
