Metadata-Version: 2.3
Name: teiphy
Version: 0.1.23
Summary: Converts TEI XML collations to NEXUS and other formats
License: MIT
Keywords: Python,phylogenetics,text encoding,TEI,NEXUS
Author: Joey McCollum and Robert Turnbull
Requires-Python: >=3.9,<4.0
Classifier: Intended Audience :: Science/Research
Classifier: License :: OSI Approved :: MIT License
Classifier: Operating System :: OS Independent
Classifier: Programming Language :: Python :: 3
Classifier: Programming Language :: Python :: 3.9
Classifier: Programming Language :: Python :: 3.10
Classifier: Programming Language :: Python :: 3.11
Classifier: Programming Language :: Python :: 3.12
Classifier: Programming Language :: Python :: 3.13
Classifier: Topic :: Software Development :: Libraries :: Python Modules
Requires-Dist: Jinja2 (>=3.1.6)
Requires-Dist: h11 (>=0.16.0)
Requires-Dist: lxml (>=4.9.3)
Requires-Dist: numpy (>=1.23.2)
Requires-Dist: openpyxl (>=3.0.10)
Requires-Dist: pandas (>=1.4.4)
Requires-Dist: python-slugify (>=6.1.2)
Requires-Dist: rich (>=12.5.1)
Requires-Dist: setuptools (>=70.0.0)
Requires-Dist: typer (>=0.6.1)
Project-URL: Documentation, https://jjmccollum.github.io/teiphy/
Project-URL: Homepage, https://github.com/jjmccollum/teiphy
Project-URL: Repository, https://github.com/jjmccollum/teiphy
